{
  "Name": "Micronesia",
  "Class": "Sub-region",
  "Parent": "Oceania",
  "Children": [
    "FSM",
    "GUM",
    "KIR",
    "MHL",
    "MNP",
    "NRU",
    "PLW",
    "UMI",
    "Micronesia"
  ],
  "ColorHex": "#63DB71",
  "ColorRGBA": [
    0.39,
    0.86,
    0.44,
    0.2
  ],
  "TransportImpactPerKgByTarget": {
    "LUX": {
      "Climate change-Total": 0.4228,
      "Climate change-Fossil": 0.4228,
      "Climate change-Biogenic": 0.0,
      "Climate change-Land use and land use change": 0.0
    }
  }
}
